examples/common_blocks.py
examples/complex_sequences.py
examples/diff_blocks.py
examples/features_transfer.py
geneblocks/Location.py
geneblocks/__init__.py
geneblocks/biotools.py
geneblocks/sequence_modification_utils.py
geneblocks/utils.py
geneblocks/version.py
geneblocks/CommonBlocks/CommonBlocks.py
geneblocks/CommonBlocks/CommonBlocksRecordTranslator.py
geneblocks/CommonBlocks/__init__.py
geneblocks/CommonBlocks/commonblocks_tools.py
geneblocks/DiffBlocks/DiffBlock.py
geneblocks/DiffBlocks/DiffBlocks.py
geneblocks/DiffBlocks/DiffRecordTranslator.py
geneblocks/DiffBlocks/__init__.py
geneblocks/DiffBlocks/diffblocks_tools.py
geneblocks-1.2.5.dist-info/licenses/LICENCE.txt
tests/test_base_diff_cases.py
tests/test_complex_sequences.py
tests/test_scenarios.py
tests/test_utils.py
geneblocks-1.2.5.dist-info/METADATA
geneblocks-1.2.5.dist-info/WHEEL
geneblocks-1.2.5.dist-info/top_level.txt
geneblocks-1.2.5.dist-info/RECORD
