Metadata-Version: 2.4
Name: geneblocks
Version: 1.2.5
Summary: Library to compare DNA sequences (diff, common blocks, etc.)
Author: Zulko
License-Expression: MIT
Project-URL: Homepage, https://github.com/Edinburgh-Genome-Foundry/Geneblocks
Keywords: DNA,sequence,blocks,diff,synthetic biology,bioinformatics
License-File: LICENCE.txt
Requires-Dist: numpy
Requires-Dist: Biopython
Requires-Dist: dna_features_viewer
Requires-Dist: networkx
Requires-Dist: python-Levenshtein
Dynamic: license-file
